tests/test_balltree.py
tests/test_coordinates.py
tests/test_angulartree.py
balltree-1.1.1.dist-info/RECORD
balltree-1.1.1.dist-info/WHEEL
balltree-1.1.1.dist-info/LICENSE
balltree-1.1.1.dist-info/top_level.txt
balltree-1.1.1.dist-info/METADATA
docs/source/conf.py
docs/source/parse_c_doc.py
src/balltree_serialize.c
src/histogram.c
src/queue.c
src/ballnode_query.c
src/ballnode.c
src/pointbuffers.c
src/balltree.c
src/ballnode_stats.c
balltree/balltree.cpython-39-x86_64-linux-gnu.so
balltree/coordinates.py
balltree/__init__.py
balltree/balltree.c
balltree/angulartree.py
