Metadata-Version: 2.1
Name: balltree
Version: 1.1.1
Summary: Fast balltree implementation for 3-dim data.
Author-email: Jan Luca van den Busch <jlvdb@astro.ruhr-uni-bochum.de>
License: GPL-3.0-or-later
Project-URL: source, https://github.com/jlvdb/balltree.git
Project-URL: documentation, https://balltree.readthedocs.io/
Classifier: Intended Audience :: Science/Research
Classifier: Topic :: Scientific/Engineering :: Astronomy
Classifier: Programming Language :: C
Classifier: Programming Language :: Python :: 3
Classifier: Programming Language :: Python :: 3.7
Classifier: Programming Language :: Python :: 3.8
Classifier: Programming Language :: Python :: 3.9
Classifier: Programming Language :: Python :: 3.10
Classifier: Programming Language :: Python :: 3.11
Classifier: Programming Language :: Python :: 3.12
Classifier: License :: OSI Approved :: GNU General Public License v3 or later (GPLv3+)
Classifier: Operating System :: Microsoft :: Windows
Classifier: Operating System :: POSIX
Classifier: Operating System :: Unix
Classifier: Operating System :: MacOS
Requires-Python: >=3.9
License-File: LICENSE
Requires-Dist: numpy >=2.0
Provides-Extra: dev
Requires-Dist: balltree[test] ; extra == 'dev'
Requires-Dist: balltree[docs] ; extra == 'dev'
Requires-Dist: isort ; extra == 'dev'
Requires-Dist: black ; extra == 'dev'
Requires-Dist: flake8 ; extra == 'dev'
Requires-Dist: pre-commit ; extra == 'dev'
Requires-Dist: ipykernel ; extra == 'dev'
Provides-Extra: docs
Requires-Dist: sphinx ; extra == 'docs'
Requires-Dist: sphinx-design ; extra == 'docs'
Requires-Dist: sphinx-copybutton ; extra == 'docs'
Requires-Dist: pydata-sphinx-theme ; extra == 'docs'
Provides-Extra: test
Requires-Dist: pytest ; extra == 'test'
